facebook_mcp_server/.env.example
facebook_mcp_server/__init__.py
facebook_mcp_server/server.py
facebook_mcp_server-0.1.0.dist-info/METADATA
facebook_mcp_server-0.1.0.dist-info/WHEEL
facebook_mcp_server-0.1.0.dist-info/entry_points.txt
facebook_mcp_server-0.1.0.dist-info/RECORD
