Metadata-Version: 2.4
Name: facebook-mcp-server
Version: 0.1.0
Summary: A simple facebook MCP server
Requires-Python: >=3.13
Requires-Dist: httpx>=0.28.1
Requires-Dist: mcp[cli]>=1.5.0
Requires-Dist: requests>=2.0.0
